tg_model/__init__.py
tg_model/cli.py
tg_model/collection.py
tg_model/csv.py
tg_model/other_files.py
tg_model/project.py
tg_model/tei.py
tg_model/util.py
tg_model/util_eltec.py
tg_model/validation.py
tg_model/xml.py
tg_model/yaml.py
tg_model/templates/README.md
tg_model/templates/avatar.png
tg_model/templates/collection_template.yaml
tg_model/templates/dummy.xslt
tg_model/templates/portalconfig.xml
tg_model/templates/project.yaml
tg_model/templates/{{ collection }}.collection
tg_model/templates/{{ collection }}.collection.meta
tg_model/templates/{{ file }}.meta
tg_model/templates/{{ id }}.edition
tg_model/templates/{{ id }}.edition.meta
tg_model/templates/{{ id }}.work
tg_model/templates/{{ id }}.work.meta
tg_model/templates/{{ id }}.xml.meta
tg_model-3.11.3.dist-info/licenses/LICENSE.txt
tg_model-3.11.3.dist-info/METADATA
tg_model-3.11.3.dist-info/WHEEL
tg_model-3.11.3.dist-info/entry_points.txt
tg_model-3.11.3.dist-info/top_level.txt
tg_model-3.11.3.dist-info/RECORD
