Metadata-Version: 2.4
Name: tg_model
Version: 3.11.3
Author: Ralf Klammer
Author-email: ralf.klammer@tu-dresden.de
License-File: LICENSE.txt
Requires-Dist: click
Requires-Dist: iso639-lang
Requires-Dist: jinja2
Requires-Dist: lxml
Requires-Dist: requests
Requires-Dist: pyaml
Dynamic: author
Dynamic: author-email
Dynamic: description
Dynamic: description-content-type
Dynamic: license-file
Dynamic: requires-dist
